odoo/addons/stock_picking_auto_create_lot/README.rst
odoo/addons/stock_picking_auto_create_lot/__init__.py
odoo/addons/stock_picking_auto_create_lot/__manifest__.py
odoo/addons/stock_picking_auto_create_lot/i18n/es.po
odoo/addons/stock_picking_auto_create_lot/i18n/it.po
odoo/addons/stock_picking_auto_create_lot/i18n/ja.po
odoo/addons/stock_picking_auto_create_lot/i18n/ja_JP.po
odoo/addons/stock_picking_auto_create_lot/i18n/nl.po
odoo/addons/stock_picking_auto_create_lot/i18n/pt.po
odoo/addons/stock_picking_auto_create_lot/i18n/pt_BR.po
odoo/addons/stock_picking_auto_create_lot/i18n/stock_picking_auto_create_lot.pot
odoo/addons/stock_picking_auto_create_lot/i18n/zh_CN.po
odoo/addons/stock_picking_auto_create_lot/models/__init__.py
odoo/addons/stock_picking_auto_create_lot/models/product.py
odoo/addons/stock_picking_auto_create_lot/models/stock_move.py
odoo/addons/stock_picking_auto_create_lot/models/stock_move_line.py
odoo/addons/stock_picking_auto_create_lot/models/stock_picking.py
odoo/addons/stock_picking_auto_create_lot/models/stock_picking_type.py
odoo/addons/stock_picking_auto_create_lot/readme/CONFIGURE.md
odoo/addons/stock_picking_auto_create_lot/readme/CONTRIBUTORS.md
odoo/addons/stock_picking_auto_create_lot/readme/DESCRIPTION.md
odoo/addons/stock_picking_auto_create_lot/readme/USAGE.md
odoo/addons/stock_picking_auto_create_lot/static/description/icon.png
odoo/addons/stock_picking_auto_create_lot/static/description/index.html
odoo/addons/stock_picking_auto_create_lot/tests/__init__.py
odoo/addons/stock_picking_auto_create_lot/tests/common.py
odoo/addons/stock_picking_auto_create_lot/tests/test_stock_picking_auto_create_lot.py
odoo/addons/stock_picking_auto_create_lot/views/product_views.xml
odoo/addons/stock_picking_auto_create_lot/views/stock_picking_type_views.xml
odoo_addon_stock_picking_auto_create_lot-18.0.1.0.0.8.dist-info/METADATA
odoo_addon_stock_picking_auto_create_lot-18.0.1.0.0.8.dist-info/WHEEL
odoo_addon_stock_picking_auto_create_lot-18.0.1.0.0.8.dist-info/top_level.txt
odoo_addon_stock_picking_auto_create_lot-18.0.1.0.0.8.dist-info/RECORD
