Metadata-Version: 2.1
Name: odoo-addon-stock_picking_auto_create_lot
Version: 18.0.1.0.0.8
Requires-Python: >=3.10
Requires-Dist: odoo==18.0.*
Summary: Auto create lots for incoming pickings
Home-page: https://github.com/OCA/stock-logistics-workflow
License: AGPL-3
Author: ACSONE SA/NV, Tecnativa, Odoo Community Association (OCA)
Author-email: support@odoo-community.org
Classifier: Programming Language :: Python
Classifier: Framework :: Odoo
Classifier: Framework :: Odoo :: 18.0
Classifier: License :: OSI Approved :: GNU Affero General Public License v3
Classifier: Development Status :: 5 - Production/Stable
